data/__init__.py
data/connect_database.py
data/edit_data.py
data/write_data_into_database.py
function/__init__.py
function/create_random_reference.py
function/get_datainfo.py
function/visualization.py
sim/__init__.py
sim/cal_groupsim.py
sim/cal_itemsim.py
GSimPy-0.0.2.dist-info/LICENSE.txt
GSimPy-0.0.2.dist-info/METADATA
GSimPy-0.0.2.dist-info/WHEEL
GSimPy-0.0.2.dist-info/top_level.txt
GSimPy-0.0.2.dist-info/RECORD
