Metadata-Version: 2.1
Name: GSimPy
Version: 0.0.2
Summary: A Python Package for calculating similarity between groups
Home-page: https://github.com/curlyae1995/GSimPy
Author: YifeiZhang
Author-email: curlyar1995@163.com
License: UNKNOWN
Platform: all
Requires-Dist: numpy
Requires-Dist: pyecharts
Requires-Dist: matplotlib
